hydra_plugins/hydra_ray_jobs_launcher/__init__.py
hydra_plugins/hydra_ray_jobs_launcher/_core.py
hydra_plugins/hydra_ray_jobs_launcher/blocking_script.py
hydra_plugins/hydra_ray_jobs_launcher/config.py
hydra_plugins/hydra_ray_jobs_launcher/container_discovery.py
hydra_plugins/hydra_ray_jobs_launcher/py.typed
hydra_plugins/hydra_ray_jobs_launcher/ray_jobs_launcher.py
hydra_ray_jobs_launcher-2.0.1.dev3.dist-info/METADATA
hydra_ray_jobs_launcher-2.0.1.dev3.dist-info/WHEEL
hydra_ray_jobs_launcher-2.0.1.dev3.dist-info/entry_points.txt
hydra_ray_jobs_launcher-2.0.1.dev3.dist-info/top_level.txt
hydra_ray_jobs_launcher-2.0.1.dev3.dist-info/RECORD
